{
  "food_use": {
    "precision": 1.0,
    "recall": 1.0,
    "f1-score": 1.0,
    "support": 25,
    "confused_with": {}
  },
  "emergency": {
    "precision": 1.0,
    "recall": 0.96,
    "f1-score": 0.9795918367346939,
    "support": 25,
    "confused_with": {
      "housing_order": 1
    }
  },
  "clothing_buy": {
    "precision": 1.0,
    "recall": 1.0,
    "f1-score": 1.0,
    "support": 25,
    "confused_with": {}
  },
  "transportation": {
    "precision": 1.0,
    "recall": 1.0,
    "f1-score": 1.0,
    "support": 25,
    "confused_with": {}
  },
  "food_buy": {
    "precision": 1.0,
    "recall": 1.0,
    "f1-score": 1.0,
    "support": 25,
    "confused_with": {}
  },
  "food_order": {
    "precision": 1.0,
    "recall": 1.0,
    "f1-score": 1.0,
    "support": 25,
    "confused_with": {}
  },
  "clothing_take": {
    "precision": 1.0,
    "recall": 1.0,
    "f1-score": 1.0,
    "support": 25,
    "confused_with": {}
  },
  "housing_electrical_controll": {
    "precision": 1.0,
    "recall": 1.0,
    "f1-score": 1.0,
    "support": 25,
    "confused_with": {}
  },
  "housing_order": {
    "precision": 0.9615384615384616,
    "recall": 1.0,
    "f1-score": 0.9803921568627451,
    "support": 25,
    "confused_with": {}
  },
  "housing_buy": {
    "precision": 1.0,
    "recall": 1.0,
    "f1-score": 1.0,
    "support": 25,
    "confused_with": {}
  },
  "housing_remind": {
    "precision": 1.0,
    "recall": 1.0,
    "f1-score": 1.0,
    "support": 25,
    "confused_with": {}
  },
  "accuracy": 0.9963636363636363,
  "macro avg": {
    "precision": 0.9965034965034966,
    "recall": 0.9963636363636365,
    "f1-score": 0.9963621812361307,
    "support": 275
  },
  "weighted avg": {
    "precision": 0.9965034965034966,
    "recall": 0.9963636363636363,
    "f1-score": 0.9963621812361307,
    "support": 275
  }
}